tree_sitter_ql_dbscheme/__init__.py
tree_sitter_ql_dbscheme/_binding.abi3.so
tree_sitter_ql_dbscheme/binding.c
tree_sitter_ql_dbscheme/__init__.pyi
tree_sitter_ql_dbscheme/py.typed
tree_sitter_ql_dbscheme-0.23.1.dist-info/top_level.txt
tree_sitter_ql_dbscheme-0.23.1.dist-info/RECORD
tree_sitter_ql_dbscheme-0.23.1.dist-info/LICENSE
tree_sitter_ql_dbscheme-0.23.1.dist-info/METADATA
tree_sitter_ql_dbscheme-0.23.1.dist-info/WHEEL
