Metadata-Version: 2.1
Name: tree-sitter-ql-dbscheme
Version: 0.23.1
Summary: QL DBScheme grammar for tree-sitter
License: MIT
Project-URL: Homepage, https://github.com/tree-sitter/tree-sitter-ql-dbscheme
Keywords: incremental,parsing,tree-sitter,ql-dbscheme
Classifier: Intended Audience :: Developers
Classifier: License :: OSI Approved :: MIT License
Classifier: Topic :: Software Development :: Compilers
Classifier: Topic :: Text Processing :: Linguistic
Classifier: Typing :: Typed
Requires-Python: >=3.9
License-File: LICENSE
Provides-Extra: core
Requires-Dist: tree-sitter~=0.22; extra == "core"
